krakenohlcvt/__init__.py
krakenohlcvt-0.1.17.dist-info/METADATA
krakenohlcvt-0.1.17.dist-info/WHEEL
krakenohlcvt-0.1.17.dist-info/RECORD
