Metadata-Version: 2.1
Name: krakenohlcvt
Version: 0.1.17
Summary: Extract symbol data as pandas data frames from the Kraken_OHLCVT.zip file of the Kraken exchange
License: MIT
Author: gwangjinkim
Author-email: gwang.jin.kim.phd@gmail.com
Requires-Python: >=3.6,<4.0
Classifier: License :: OSI Approved :: MIT License
Classifier: Programming Language :: Python :: 3
Classifier: Programming Language :: Python :: 3.6
Classifier: Programming Language :: Python :: 3.7
Classifier: Programming Language :: Python :: 3.8
Classifier: Programming Language :: Python :: 3.9
Classifier: Programming Language :: Python :: 3.10
Classifier: Programming Language :: Python :: 3.11
Classifier: Programming Language :: Python :: 3.12
Requires-Dist: pandas
